SkibidiPython/__init__.py
SkibidiPython/package.py
skibidipython-0.3.0.dist-info/licenses/LICENSE
skibidipython-0.3.0.dist-info/METADATA
skibidipython-0.3.0.dist-info/WHEEL
skibidipython-0.3.0.dist-info/top_level.txt
skibidipython-0.3.0.dist-info/RECORD
